[
  {
    "name": "星",
    "element": "PHYSICAL",
    "energy_limit": 120,
    "stat": {
      "base_max_hp": 4500,
      "base_atk": 2000,
      "base_def": 1000,
      "base_spd": 150,
      "hp_pct": 0.0,
      "atk_pct": 0.0,
      "def_pct": 0.0,
      "spd_pct": 0.0,
      "hp_flat": 0,
      "atk_flat": 0,
      "def_flat": 0,
      "crit_rate": 0.8,
      "crit_dmg": 1.5,
      "effect_hit": 0.0,
      "effect_res": 0.0,
      "dmg_pct": 0.0,
      "break_efficiency": 1.0,
      "energy_recovery_rate": 1.0,
      "physical_dmg_pct": 40.0,
      "wind_dmg_pct": 0.0,
      "thunder_dmg_pct": 0.0,
      "fire_dmg_pct": 0.0,
      "ice_dmg_pct": 0.0,
      "quantum_dmg_pct": 0.0,
      "imaginary_dmg_pct": 0.0,
      "physical_res_pct": 0.0,
      "wind_res_pct": 0.0,
      "thunder_res_pct": 0.0,
      "fire_res_pct": 0.0,
      "ice_res_pct": 0.0,
      "quantum_res_pct": 0.0,
      "imaginary_res_pct": 0.0
    }
  },
  {
    "name": "三月萤",
    "element": "WIND",
    "energy_limit": 120,
    "stat": {
      "base_max_hp": 4500,
      "base_atk": 2000,
      "base_def": 1000,
      "base_spd": 150,
      "hp_pct": 0.0,
      "atk_pct": 0.0,
      "def_pct": 0.0,
      "spd_pct": 0.0,
      "hp_flat": 0,
      "atk_flat": 0,
      "def_flat": 0,
      "crit_rate": 0.8,
      "crit_dmg": 1.5,
      "effect_hit": 0.0,
      "effect_res": 0.0,
      "dmg_pct": 0.0,
      "break_efficiency": 1.0,
      "energy_recovery_rate": 1.0,
      "physical_dmg_pct": 0.0,
      "wind_dmg_pct": 40.0,
      "thunder_dmg_pct": 0.0,
      "fire_dmg_pct": 0.0,
      "ice_dmg_pct": 0.0,
      "quantum_dmg_pct": 0.0,
      "imaginary_dmg_pct": 0.0,
      "physical_res_pct": 0.0,
      "wind_res_pct": 0.0,
      "thunder_res_pct": 0.0,
      "fire_res_pct": 0.0,
      "ice_res_pct": 0.0,
      "quantum_res_pct": 0.0,
      "imaginary_res_pct": 0.0
    }
  },
  {
    "name": "丹恒",
    "element": "THUNDER",
    "energy_limit": 120,
    "stat": {
      "base_max_hp": 4500,
      "base_atk": 2000,
      "base_def": 1000,
      "base_spd": 150,
      "hp_pct": 0.0,
      "atk_pct": 0.0,
      "def_pct": 0.0,
      "spd_pct": 0.0,
      "hp_flat": 0,
      "atk_flat": 0,
      "def_flat": 0,
      "crit_rate": 0.05,
      "crit_dmg": 1.5,
      "effect_hit": 0.0,
      "effect_res": 0.0,
      "dmg_pct": 0.0,
      "break_efficiency": 1.0,
      "energy_recovery_rate": 1.0,
      "physical_dmg_pct": 0.0,
      "wind_dmg_pct": 0.0,
      "thunder_dmg_pct": 40.0,
      "fire_dmg_pct": 0.0,
      "ice_dmg_pct": 0.0,
      "quantum_dmg_pct": 0.0,
      "imaginary_dmg_pct": 0.0,
      "physical_res_pct": 0.0,
      "wind_res_pct": 0.0,
      "thunder_res_pct": 0.0,
      "fire_res_pct": 0.0,
      "ice_res_pct": 0.0,
      "quantum_res_pct": 0.0,
      "imaginary_res_pct": 0.0
    }
  },
  {
    "name": "姬子",
    "element": "FIRE",
    "energy_limit": 120,
    "stat": {
      "base_max_hp": 4500,
      "base_atk": 2000,
      "base_def": 1000,
      "base_spd": 150,
      "hp_pct": 0.0,
      "atk_pct": 0.0,
      "def_pct": 0.0,
      "spd_pct": 0.0,
      "hp_flat": 0,
      "atk_flat": 0,
      "def_flat": 0,
      "crit_rate": 0.05,
      "crit_dmg": 1.5,
      "effect_hit": 0.0,
      "effect_res": 0.0,
      "dmg_pct": 0.0,
      "break_efficiency": 1.0,
      "energy_recovery_rate": 1.0,
      "physical_dmg_pct": 0.0,
      "wind_dmg_pct": 0.0,
      "thunder_dmg_pct": 0.0,
      "fire_dmg_pct": 40.0,
      "ice_dmg_pct": 0.0,
      "quantum_dmg_pct": 0.0,
      "imaginary_dmg_pct": 0.0,
      "physical_res_pct": 0.0,
      "wind_res_pct": 0.0,
      "thunder_res_pct": 0.0,
      "fire_res_pct": 0.0,
      "ice_res_pct": 0.0,
      "quantum_res_pct": 0.0,
      "imaginary_res_pct": 0.0
    }
  },
  {
    "name": "布洛妮娅",
    "element": "ICE",
    "energy_limit": 120,
    "stat": {
      "base_max_hp": 4500,
      "base_atk": 2000,
      "base_def": 1000,
      "base_spd": 150,
      "hp_pct": 0.0,
      "atk_pct": 0.0,
      "def_pct": 0.0,
      "spd_pct": 0.0,
      "hp_flat": 0,
      "atk_flat": 0,
      "def_flat": 0,
      "crit_rate": 0.05,
      "crit_dmg": 1.5,
      "effect_hit": 0.0,
      "effect_res": 0.0,
      "dmg_pct": 0.0,
      "break_efficiency": 1.0,
      "energy_recovery_rate": 1.0,
      "physical_dmg_pct": 0.0,
      "wind_dmg_pct": 0.0,
      "thunder_dmg_pct": 0.0,
      "fire_dmg_pct": 0.0,
      "ice_dmg_pct": 40.0,
      "quantum_dmg_pct": 0.0,
      "imaginary_dmg_pct": 0.0,
      "physical_res_pct": 0.0,
      "wind_res_pct": 0.0,
      "thunder_res_pct": 0.0,
      "fire_res_pct": 0.0,
      "ice_res_pct": 0.0,
      "quantum_res_pct": 0.0,
      "imaginary_res_pct": 0.0
    }
  },
  {
    "name": "银狼",
    "element": "QUANTUM",
    "energy_limit": 120,
    "stat": {
      "base_max_hp": 4500,
      "base_atk": 2000,
      "base_def": 1000,
      "base_spd": 150,
      "hp_pct": 0.0,
      "atk_pct": 0.0,
      "def_pct": 0.0,
      "spd_pct": 0.0,
      "hp_flat": 0,
      "atk_flat": 0,
      "def_flat": 0,
      "crit_rate": 0.05,
      "crit_dmg": 1.5,
      "effect_hit": 0.0,
      "effect_res": 0.0,
      "dmg_pct": 0.0,
      "break_efficiency": 1.0,
      "energy_recovery_rate": 1.0,
      "physical_dmg_pct": 0.0,
      "wind_dmg_pct": 0.0,
      "thunder_dmg_pct": 0.0,
      "fire_dmg_pct": 0.0,
      "ice_dmg_pct": 0.0,
      "quantum_dmg_pct": 40.0,
      "imaginary_dmg_pct": 0.0,
      "physical_res_pct": 0.0,
      "wind_res_pct": 0.0,
      "thunder_res_pct": 0.0,
      "fire_res_pct": 0.0,
      "ice_res_pct": 0.0,
      "quantum_res_pct": 0.0,
      "imaginary_res_pct": 0.0
    }
  },
  {
    "name": "瓦尔特",
    "element": "IMAGINARY",
    "energy_limit": 120,
    "stat": {
      "base_max_hp": 4500,
      "base_atk": 2000,
      "base_def": 1000,
      "base_spd": 150,
      "hp_pct": 0.0,
      "atk_pct": 0.0,
      "def_pct": 0.0,
      "spd_pct": 0.0,
      "hp_flat": 0,
      "atk_flat": 0,
      "def_flat": 0,
      "crit_rate": 0.05,
      "crit_dmg": 1.5,
      "effect_hit": 0.0,
      "effect_res": 0.0,
      "dmg_pct": 0.0,
      "break_efficiency": 1.0,
      "energy_recovery_rate": 1.0,
      "physical_dmg_pct": 0.0,
      "wind_dmg_pct": 0.0,
      "thunder_dmg_pct": 0.0,
      "fire_dmg_pct": 0.0,
      "ice_dmg_pct": 0.0,
      "quantum_dmg_pct": 0.0,
      "imaginary_dmg_pct": 40.0,
      "physical_res_pct": 0.0,
      "wind_res_pct": 0.0,
      "thunder_res_pct": 0.0,
      "fire_res_pct": 0.0,
      "ice_res_pct": 0.0,
      "quantum_res_pct": 0.0,
      "imaginary_res_pct": 0.0
    }
  }
]
